ai4climate/__init__.py
ai4climate/buildingelectricity.py
ai4climate/dataset_utils.py
ai4climate/load.py
ai4climate/opfdata.py
ai4climate/powergraph.py
ai4climate/solarcube.py
ai4climate/windfarm.py
ai4climate-0.0.4.dist-info/METADATA
ai4climate-0.0.4.dist-info/WHEEL
ai4climate-0.0.4.dist-info/top_level.txt
ai4climate-0.0.4.dist-info/RECORD
