Metadata-Version: 2.4
Name: ai4climate
Version: 0.0.4
Summary: A Collection and Analysis of Machine Learning Tasks, Datasets and Testbeds for Tackling Climate Change.
Author-email: Arsam Aryandoust <arsam@mit.edu>
License: MIT License
Project-URL: Source, https://github.com/ArsamAryandoust/AI4Climate
Project-URL: Documentation, https://readthedocs.org/projects/AI4Climate
Keywords: Artificial Intelligence,Climate Change,Machine Learning
Classifier: Programming Language :: Python :: 3
Classifier: Operating System :: OS Independent
Requires-Python: >=3.9
Requires-Dist: numpy>=2.0
Requires-Dist: pandas>=2.0
Requires-Dist: h5py>=3.0.0
Requires-Dist: torch>=2.0.0
